odoo/addons/partner_identification_eori/README.rst
odoo/addons/partner_identification_eori/__init__.py
odoo/addons/partner_identification_eori/__manifest__.py
odoo/addons/partner_identification_eori/data/partner_identification_eori.xml
odoo/addons/partner_identification_eori/i18n/it.po
odoo/addons/partner_identification_eori/i18n/partner_identification_eori.pot
odoo/addons/partner_identification_eori/models/__init__.py
odoo/addons/partner_identification_eori/models/res_partner_id_category.py
odoo/addons/partner_identification_eori/readme/CONTRIBUTORS.md
odoo/addons/partner_identification_eori/readme/DESCRIPTION.md
odoo/addons/partner_identification_eori/static/description/icon.svg
odoo/addons/partner_identification_eori/static/description/index.html
odoo/addons/partner_identification_eori/tests/__init__.py
odoo/addons/partner_identification_eori/tests/test_eori.py
odoo_addon_partner_identification_eori-18.0.1.0.0.2.dist-info/METADATA
odoo_addon_partner_identification_eori-18.0.1.0.0.2.dist-info/WHEEL
odoo_addon_partner_identification_eori-18.0.1.0.0.2.dist-info/top_level.txt
odoo_addon_partner_identification_eori-18.0.1.0.0.2.dist-info/RECORD
